<?xml version="1.0" encoding="UTF-8"?><items iblockUid="hut:contacts" exchangeVersion="2"><item><field name="ACTIVE"><value>Y</value></field><field name="ACTIVE_FROM"/><field name="ACTIVE_TO"/><field name="SORT"><value>500</value></field><field name="NAME"><value>Санкт-Петербург, Петроградская наб, 18А</value></field><field name="PREVIEW_PICTURE"/><field name="PREVIEW_TEXT"/><field name="PREVIEW_TEXT_TYPE"><value>text</value></field><field name="DETAIL_PICTURE"/><field name="DETAIL_TEXT"/><field name="DETAIL_TEXT_TYPE"><value>text</value></field><field name="CODE"/><field name="TAGS"/><field name="XML_ID"><value>42</value></field><field name="IBLOCK_SECTION"/><property name="PHONE"><value>8 800 000 00 00</value></property><property name="MAIL"><value>mail@mail.ru</value></property><property name="MAP"><value>&amp;lt;div style=&amp;quot;position:relative;overflow:hidden;&amp;quot;&amp;gt;&amp;lt;a href=&amp;quot;https://yandex.ru/maps/org/quarta_oruzheyny_kvartal/89423755221/?utm_medium=mapframe&amp;utm_source=maps&amp;quot; style=&amp;quot;color:#eee;font-size:12px;position:absolute;top:0px;&amp;quot;&amp;gt;Quarta Оружейный квартал&amp;lt;/a&amp;gt;&amp;lt;a href=&amp;quot;https://yandex.ru/maps/2/saint-petersburg/category/weapons_and_self_defense/184105348/?utm_medium=mapframe&amp;utm_source=maps&amp;quot; style=&amp;quot;color:#eee;font-size:12px;position:absolute;top:14px;&amp;quot;&amp;gt;Оружие и средства самозащиты в Санкт‑Петербурге&amp;lt;/a&amp;gt;&amp;lt;a href=&amp;quot;https://yandex.ru/maps/2/saint-petersburg/category/hunting_supplies/184107353/?utm_medium=mapframe&amp;utm_source=maps&amp;quot; style=&amp;quot;color:#eee;font-size:12px;position:absolute;top:28px;&amp;quot;&amp;gt;Товары для охоты в Санкт‑Петербурге&amp;lt;/a&amp;gt;&amp;lt;iframe src=&amp;quot;https://yandex.ru/map-widget/v1/org/quarta_oruzheyny_kvartal/89423755221/?ll=30.322940%2C59.845254&amp;z=16.6&amp;quot; width=&amp;quot;560&amp;quot; height=&amp;quot;400&amp;quot; frameborder=&amp;quot;0&amp;quot; allowfullscreen=&amp;quot;true&amp;quot; style=&amp;quot;position:relative;&amp;quot;&amp;gt;&amp;lt;/iframe&amp;gt;&amp;lt;/div&amp;gt;</value></property><property name="OPENING_SOON"><value>YES</value></property></item><item><field name="ACTIVE"><value>Y</value></field><field name="ACTIVE_FROM"/><field name="ACTIVE_TO"/><field name="SORT"><value>500</value></field><field name="NAME"><value>Санкт-Петербург, Московский проспект, д.221</value></field><field name="PREVIEW_PICTURE"/><field name="PREVIEW_TEXT"/><field name="PREVIEW_TEXT_TYPE"><value>text</value></field><field name="DETAIL_PICTURE"/><field name="DETAIL_TEXT"/><field name="DETAIL_TEXT_TYPE"><value>text</value></field><field name="CODE"/><field name="TAGS"/><field name="XML_ID"><value>43</value></field><field name="IBLOCK_SECTION"/><property name="PHONE"><value>8 800 000 00 00</value></property><property name="MAIL"><value>mail@mail.ru</value></property><property name="MAP"><value>&amp;lt;div style=&amp;quot;position:relative;overflow:hidden;&amp;quot;&amp;gt;&amp;lt;a href=&amp;quot;https://yandex.ru/maps/org/quarta_oruzheyny_kvartal/89423755221/?utm_medium=mapframe&amp;utm_source=maps&amp;quot; style=&amp;quot;color:#eee;font-size:12px;position:absolute;top:0px;&amp;quot;&amp;gt;Quarta Оружейный квартал&amp;lt;/a&amp;gt;&amp;lt;a href=&amp;quot;https://yandex.ru/maps/2/saint-petersburg/category/weapons_and_self_defense/184105348/?utm_medium=mapframe&amp;utm_source=maps&amp;quot; style=&amp;quot;color:#eee;font-size:12px;position:absolute;top:14px;&amp;quot;&amp;gt;Оружие и средства самозащиты в Санкт‑Петербурге&amp;lt;/a&amp;gt;&amp;lt;a href=&amp;quot;https://yandex.ru/maps/2/saint-petersburg/category/hunting_supplies/184107353/?utm_medium=mapframe&amp;utm_source=maps&amp;quot; style=&amp;quot;color:#eee;font-size:12px;position:absolute;top:28px;&amp;quot;&amp;gt;Товары для охоты в Санкт‑Петербурге&amp;lt;/a&amp;gt;&amp;lt;iframe src=&amp;quot;https://yandex.ru/map-widget/v1/org/quarta_oruzheyny_kvartal/89423755221/?ll=30.322940%2C59.845254&amp;z=16.6&amp;quot; width=&amp;quot;560&amp;quot; height=&amp;quot;400&amp;quot; frameborder=&amp;quot;0&amp;quot; allowfullscreen=&amp;quot;true&amp;quot; style=&amp;quot;position:relative;&amp;quot;&amp;gt;&amp;lt;/iframe&amp;gt;&amp;lt;/div&amp;gt;</value></property><property name="OPENING_SOON"/></item></items>